fontGit/__init__.py
fontGit/errors.py
fontGit/objects/font.py
fontGit/utils.py
fontgit-0.0.7.dist-info/LICENSE
fontgit-0.0.7.dist-info/METADATA
fontgit-0.0.7.dist-info/WHEEL
fontgit-0.0.7.dist-info/RECORD
