Metadata-Version: 2.3
Name: fontGit
Version: 0.0.7
Summary: A tool for versioning font files with Git.
License: MIT
Keywords: font,git,ufo,version-control
Author: Bahman Eslami
Author-email: eslami.bahman@gmail.com
Requires-Python: >=3.11
Classifier: Development Status :: 3 - Alpha
Classifier: Intended Audience :: Developers
Classifier: License :: OSI Approved :: MIT License
Classifier: Programming Language :: Python :: 3
Classifier: Programming Language :: Python :: 3.11
Classifier: Topic :: Software Development :: Version Control
Classifier: Topic :: Text Processing :: Fonts
Requires-Dist: fs (>=2.4.16,<3.0.0)
Requires-Dist: gitpython (>=3.1.44,<4.0.0)
Requires-Dist: ufolib2 (>=0.17.1,<0.18.0)
Project-URL: Bug Tracker, https://github.com/typoman/fontgit/issues
Project-URL: Homepage, https://github.com/typoman/fontgit
Project-URL: Repository, https://github.com/typoman/fontgit
